AUTHORS
LICENSE
MANIFEST.in
README.md
setup.py
mamba/__init__.py
mamba/_version.py
mamba/copyright.py
mamba/license.py
mamba/plugin.py
mamba/application/__init__.py
mamba/application/app.py
mamba/application/appstyles.py
mamba/application/controller.py
mamba/application/model.py
mamba/application/scripts.py
mamba/core/__init__.py
mamba/core/adapters.py
mamba/core/decorators.py
mamba/core/interfaces.py
mamba/core/module.py
mamba/core/resource.py
mamba/core/session.py
mamba/core/templating.py
mamba/core/services/__init__.py
mamba/core/services/threadpool.py
mamba/deployment/__init__.py
mamba/deployment/deployer.py
mamba/deployment/fabric_deployer.py
mamba/enterprise/__init__.py
mamba/enterprise/common.py
mamba/enterprise/database.py
mamba/enterprise/mysql.py
mamba/enterprise/postgres.py
mamba/enterprise/sqlite.py
mamba/http/__init__.py
mamba/http/headers.py
mamba/scripts/__init__.py
mamba/scripts/_controller.py
mamba/scripts/_model.py
mamba/scripts/_project.py
mamba/scripts/_sql.py
mamba/scripts/_view.py
mamba/scripts/commons.py
mamba/scripts/mamba_admin.py
mamba/scripts/test/__init__.py
mamba/scripts/test/test_commons.py
mamba/scripts/test/test_mamba_admin.py
mamba/templates/application.json.tpl
mamba/templates/controller.tpl
mamba/templates/database.json.tpl
mamba/templates/factory.tpl
mamba/templates/favicon.ico.tpl
mamba/templates/layout.tpl
mamba/templates/mamba_services.tpl
mamba/templates/model.tpl
mamba/templates/plugin.tpl
mamba/templates/version.tpl
mamba/templates/view.tpl
mamba/templates/jinja/root_page.html
mamba/templates/jinja/test.html
mamba/test/__init__.py
mamba/test/test_application.py
mamba/test/test_borg.py
mamba/test/test_camelcase.py
mamba/test/test_config.py
mamba/test/test_controller.py
mamba/test/test_converter.py
mamba/test/test_database.py
mamba/test/test_decorators.py
mamba/test/test_deployer.py
mamba/test/test_fabric.py
mamba/test/test_headers.py
mamba/test/test_less.py
mamba/test/test_mamba.py
mamba/test/test_model.py
mamba_framework.egg-info/PKG-INFO
mamba_framework.egg-info/SOURCES.txt
mamba_framework.egg-info/dependency_links.txt
mamba_framework.egg-info/entry_points.txt
mamba_framework.egg-info/not-zip-safe
mamba_framework.egg-info/requires.txt
mamba_framework.egg-info/top_level.txt